Metadata-Version: 2.1
Name: Orange3-Timeseries-zh
Version: 0.3.4
Summary: Orange3 add-on for exploring time series and sequential data.
Home-page: https://github.com/biolab/orange3-timeseries
Author: Bioinformatics Laboratory, FRI UL
Author-email: info@biolab.si
License: CC-BY-NC-3.0
Keywords: time series,sequence analysis,orange3 add-on,ARIMA,VAR model,forecast
Platform: UNKNOWN
Classifier: Development Status :: 4 - Beta
Classifier: Environment :: X11 Applications :: Qt
Classifier: Environment :: Plugins
Classifier: Programming Language :: Python
Classifier: License :: Other/Proprietary License
Classifier: Operating System :: OS Independent
Classifier: Topic :: Scientific/Engineering :: Artificial Intelligence
Classifier: Topic :: Scientific/Engineering :: Visualization
Classifier: Topic :: Software Development :: Libraries :: Python Modules
Classifier: Intended Audience :: Education
Classifier: Intended Audience :: Science/Research
Classifier: Intended Audience :: Developers
Requires-Dist: Orange3-zh
Requires-Dist: statsmodels (>=0.10.0)
Requires-Dist: pandas
Requires-Dist: pandas-datareader
Requires-Dist: numpy
Requires-Dist: scipy (>=0.17)
